micropython_tcs3430/__init__.py
micropython_tcs3430/i2c_helpers.py
micropython_tcs3430/tcs3430.py
micropython_tcs3430-0.1.0.dist-info/LICENSE
micropython_tcs3430-0.1.0.dist-info/METADATA
micropython_tcs3430-0.1.0.dist-info/WHEEL
micropython_tcs3430-0.1.0.dist-info/top_level.txt
micropython_tcs3430-0.1.0.dist-info/RECORD
