Metadata-Version: 2.1
Name: micropython-tcs3430
Version: 0.1.0
Summary: MicroPython driver for the AMS TCS3430 Color and ALS sensor
Author-email: JDM <xxyx@mailmeto.mozmail.com>
License: MIT
Project-URL: Homepage, https://github.com/jposada202020/MicroPython_TCS3430
Keywords: sensor,micropython,tcs3430,sensor,als,color,tcs3430,ams,driver,micropython
Classifier: Intended Audience :: Developers
Classifier: Topic :: Software Development :: Libraries
Classifier: Topic :: Software Development :: Embedded Systems
Classifier: Topic :: System :: Hardware
Classifier: License :: OSI Approved :: MIT License
Classifier: Programming Language :: Python :: Implementation :: MicroPython
License-File: LICENSE
